AUTHORS
COPYING
MANIFEST.in
README
setup.cfg
setup.py
pgpagecache/__init__.py
pgpagecache/pgpagecache.py
pgpagecache.egg-info/PKG-INFO
pgpagecache.egg-info/SOURCES.txt
pgpagecache.egg-info/dependency_links.txt
pgpagecache.egg-info/entry_points.txt
pgpagecache.egg-info/requires.txt
pgpagecache.egg-info/top_level.txt