Metadata-Version: 1.1
Name: pgpagecache
Version: 0.1
Summary: PostgreSQL objects resident in OS memory
Home-page: UNKNOWN
Author: Chrysostomos Nanakos
Author-email: chris@include.gr
License: GPL
Keywords: PostgreSQL postgres pagecache linux cache buffercache buffer memory
Platform: posix
Classifier: Environment :: Console
Classifier: License :: OSI Approved :: GNU General Public License v3 or later (GPLv3+)
Classifier: Operating System :: POSIX :: Linux
Classifier: Topic :: Utilities
Classifier: Intended Audience :: Developers
Classifier: Intended Audience :: System Administrators
